LICENSE
MANIFEST.in
README.md
druuid.py
setup.py
Druuid.egg-info/PKG-INFO
Druuid.egg-info/SOURCES.txt
Druuid.egg-info/dependency_links.txt
Druuid.egg-info/top_level.txt