Metadata-Version: 1.1
Name: Druuid
Version: 0.1.1
Summary: A time relative identifier
Home-page: https://github.com/lrnt/pydruuid
Author: Laurent De Marez
Author-email: laurent@demarez.org
License: MIT
Platform: UNKNOWN
Classifier: Development Status :: 4 - Beta
Classifier: Topic :: Utilities
Classifier: License :: OSI Approved :: MIT License
